#ロボット名(deago4)
<mem_w size="1" adr="0x0020">0x64,0x65,0x61,0x67,0x6f,0x34</mem_w>

#基本制御周期
<mem_w size="4" adr="0x0040">16667</mem_w>

#音声のアッテネータ
<mem_w size="2" adr="0x0046">0x0000</mem_w>

#補間方法（128個）
<mem_w size="1" adr="0x0b80">
	1,3,1,3,1,3,1,3,
	1,3,1,3,1,3,1,3,
	1,3,1,3,1,3,1,3,
	1,3,1,3,1,3,1,3,
	1,3,1,3,1,3,1,3,
	1,3,1,3,1,3,1,3,
	1,1,1,1,1,1,1,1,
	1,1,1,1,1,1,1,1,
	1,1,1,1,1,1,1,3,
	1,1,1,1,1,1,1,1,
	1,1,1,1,1,1,1,1,
	1,1,1,1,1,1,1,1,
	1,1,1,1,1,1,1,1,
	1,1,1,1,1,1,1,1,
	1,1,1,1,1,1,1,1,
	1,1,1,1,1,1,1,1
</mem_w>

#モータの設定（64個）
#  ADRRDP,ADR0,ADREN,ADROVR,K0,OFS,LIML,LIMH,
#  ADR2A,ADR2B,K3,ADR3A,ADR3B,K4,ADR4A,ADR4B,
#  (ONDELAY<<8) + KSIGN,SOFTST,SU16_ADRRDMT,reserved...
#MOT0 "ID1"
<medit>	<motor name="ID1" data="0"/>
</medit>
<mem_w size="2" adr="0x1000">
	0x0d80,0x0c00,0x0c02,0x0d00,0x0100,0x0000,0x8001,0x7fff,
	0x0000,0x0000,0x0000,0x0000,0x0000,0x0000,0x0000,0x0000,
	0x0000,0x0000,0x0000,0x0000,0x0000,0x003c,0x0000,0x0000,
	0x0000,0x0000,0x0000,0x0000,0x0000,0x0000,0x0000,0x0000
</mem_w>

#MOT1 "ID2"
<medit>	<motor name="ID2" data="1"/>
</medit>
<mem_w size="2" adr="0x1040">
	0x0d82,0x0c04,0x0c06,0x0d02,0x0100,0x0019,0x8001,0x7fff,
	0x0000,0x0000,0x0000,0x0000,0x0000,0x0000,0x0000,0x0000,
	0x0000,0x0000,0x0000,0x0000,0x0000,0x003c,0x0000,0x0000,
	0x0000,0x0000,0x0000,0x0000,0x0000,0x0000,0x0000,0x0000
</mem_w>

#MOT2 "ID3"
<medit>	<motor name="ID3" data="2"/>
</medit>
<mem_w size="2" adr="0x1080">
	0x0d84,0x0c08,0x0c0a,0x0d04,0x0100,0x0078,0x8001,0x7fff,
	0x0000,0x0000,0x0000,0x0000,0x0000,0x0000,0x0000,0x0000,
	0x0000,0x0000,0x0000,0x0000,0x0000,0x003c,0x0000,0x0000,
	0x0000,0x0000,0x0000,0x0000,0x0000,0x0000,0x0000,0x0000
</mem_w>

#MOT3 "ID4"
<medit>	<motor name="ID4" data="3"/>
</medit>
<mem_w size="2" adr="0x10c0">
	0x0d86,0x0c0c,0x0c0e,0x0d06,0x0100,0xfed4,0x8001,0x7fff,
	0x0000,0x0000,0x0000,0x0000,0x0000,0x0000,0x0000,0x0000,
	0x0000,0x0000,0x0000,0x0000,0x0000,0x003c,0x0000,0x0000,
	0x0000,0x0000,0x0000,0x0000,0x0000,0x0000,0x0000,0x0000
</mem_w>

#MOT4 "ID5"
<medit>	<motor name="ID5" data="4"/>
</medit>
<mem_w size="2" adr="0x1100">
	0x0d88,0x0c10,0x0c12,0x0d08,0x0100,0x0073,0x8001,0x7fff,
	0x0000,0x0000,0x0000,0x0000,0x0000,0x0000,0x0000,0x0000,
	0x0000,0x0000,0x0000,0x0000,0x0000,0x003c,0x0000,0x0000,
	0x0000,0x0000,0x0000,0x0000,0x0000,0x0000,0x0000,0x0000
</mem_w>

#MOT5 "ID6"
<medit>	<motor name="ID6" data="5"/>
</medit>
<mem_w size="2" adr="0x1140">
	0x0d8a,0x0c14,0x0c16,0x0d0a,0x0100,0xffec,0x8001,0x7fff,
	0x0000,0x0000,0x0000,0x0000,0x0000,0x0000,0x0000,0x0000,
	0x0000,0x0000,0x0000,0x0000,0x0000,0x003c,0x0000,0x0000,
	0x0000,0x0000,0x0000,0x0000,0x0000,0x0000,0x0000,0x0000
</mem_w>

#MOT6 "ID7"
<medit>	<motor name="ID7" data="6"/>
</medit>
<mem_w size="2" adr="0x1180">
	0x0d8c,0x0c18,0x0c1a,0x0d0c,0x0100,0xfff1,0x8001,0x7fff,
	0x0000,0x0000,0x0000,0x0000,0x0000,0x0000,0x0000,0x0000,
	0x0000,0x0000,0x0000,0x0000,0x0000,0x003c,0x0000,0x0000,
	0x0000,0x0000,0x0000,0x0000,0x0000,0x0000,0x0000,0x0000
</mem_w>

#MOT7 "ID8"
<medit>	<motor name="ID8" data="7"/>
</medit>
<mem_w size="2" adr="0x11c0">
	0x0d8e,0x0c1c,0x0c1e,0x0d0e,0x0100,0xff88,0x8001,0x7fff,
	0x0000,0x0000,0x0000,0x0000,0x0000,0x0000,0x0000,0x0000,
	0x0000,0x0000,0x0000,0x0000,0x0000,0x003c,0x0000,0x0000,
	0x0000,0x0000,0x0000,0x0000,0x0000,0x0000,0x0000,0x0000
</mem_w>

#MOT8 "ID9"
<medit>	<motor name="ID9" data="8"/>
</medit>
<mem_w size="2" adr="0x1200">
	0x0d90,0x0c20,0x0c22,0x0d10,0x0100,0x0104,0x8001,0x7fff,
	0x0000,0x0000,0x0000,0x0000,0x0000,0x0000,0x0000,0x0000,
	0x0000,0x0000,0x0000,0x0000,0x0000,0x003c,0x0000,0x0000,
	0x0000,0x0000,0x0000,0x0000,0x0000,0x0000,0x0000,0x0000
</mem_w>

#MOT9 "ID10"
<medit>	<motor name="ID10" data="9"/>
</medit>
<mem_w size="2" adr="0x1240">
	0x0d92,0x0c24,0x0c26,0x0d12,0x0100,0xff6f,0x8001,0x7fff,
	0x0000,0x0000,0x0000,0x0000,0x0000,0x0000,0x0000,0x0000,
	0x0000,0x0000,0x0000,0x0000,0x0000,0x003c,0x0000,0x0000,
	0x0000,0x0000,0x0000,0x0000,0x0000,0x0000,0x0000,0x0000
</mem_w>

#MOT10 "ID11"
<medit>	<motor name="ID11" data="10"/>
</medit>
<mem_w size="2" adr="0x1280">
	0x0d94,0x0c28,0x0c2a,0x0d14,0x0100,0x0023,0x8001,0x7fff,
	0x0000,0x0000,0x0000,0x0000,0x0000,0x0000,0x0000,0x0000,
	0x0000,0x0000,0x0000,0x0000,0x0000,0x003c,0x0000,0x0000,
	0x0000,0x0000,0x0000,0x0000,0x0000,0x0000,0x0000,0x0000
</mem_w>

#MOT11 "ID12"
<medit>	<motor name="ID12" data="11"/>
</medit>
<mem_w size="2" adr="0x12c0">
	0x0d96,0x0c2c,0x0c2e,0x0d16,0x0100,0x0014,0x8001,0x7fff,
	0x0000,0x0000,0x0000,0x0000,0x0000,0x0000,0x0000,0x0000,
	0x0000,0x0000,0x0000,0x0000,0x0000,0x003c,0x0000,0x0000,
	0x0000,0x0000,0x0000,0x0000,0x0000,0x0000,0x0000,0x0000
</mem_w>

#MOT12 "ID13"
<medit>	<motor name="ID13" data="12"/>
</medit>
<mem_w size="2" adr="0x1300">
	0x0d98,0x0c30,0x0c32,0x0d18,0x0100,0x0014,0x8001,0x7fff,
	0x0000,0x0000,0x0000,0x0000,0x0000,0x0000,0x0000,0x0000,
	0x0000,0x0000,0x0000,0x0000,0x0000,0x003c,0x0000,0x0000,
	0x0000,0x0000,0x0000,0x0000,0x0000,0x0000,0x0000,0x0000
</mem_w>

#MOT13 "ID14"
<medit>	<motor name="ID14" data="13"/>
</medit>
<mem_w size="2" adr="0x1340">
	0x0d9a,0x0c34,0x0c36,0x0d1a,0x0100,0x004b,0x8001,0x7fff,
	0x0000,0x0000,0x0000,0x0000,0x0000,0x0000,0x0000,0x0000,
	0x0000,0x0000,0x0000,0x0000,0x0000,0x003c,0x0000,0x0000,
	0x0000,0x0000,0x0000,0x0000,0x0000,0x0000,0x0000,0x0000
</mem_w>

#MOT14 "ID15"
<medit>	<motor name="ID15" data="14"/>
</medit>
<mem_w size="2" adr="0x1380">
	0x0d9c,0x0c38,0x0c3a,0x0d1c,0x0100,0xffab,0x8001,0x7fff,
	0x0000,0x0000,0x0000,0x0000,0x0000,0x0000,0x0000,0x0000,
	0x0000,0x0000,0x0000,0x0000,0x0000,0x003c,0x0000,0x0000,
	0x0000,0x0000,0x0000,0x0000,0x0000,0x0000,0x0000,0x0000
</mem_w>

#MOT15 "ID16"
<medit>	<motor name="ID16" data="15"/>
</medit>
<mem_w size="2" adr="0x13c0">
	0x0d9e,0x0c3c,0x0c3e,0x0d1e,0x0100,0xffe2,0x8001,0x7fff,
	0x0000,0x0000,0x0000,0x0000,0x0000,0x0000,0x0000,0x0000,
	0x0000,0x0000,0x0000,0x0000,0x0000,0x003c,0x0000,0x0000,
	0x0000,0x0000,0x0000,0x0000,0x0000,0x0000,0x0000,0x0000
</mem_w>

#MOT16 "ID17"
<medit>	<motor name="ID17" data="16"/>
</medit>
<mem_w size="2" adr="0x1400">
	0x0da0,0x0c40,0x0c42,0x0d20,0x0100,0x0262,0x8001,0x7fff,
	0x0000,0x0000,0x0000,0x0000,0x0000,0x0000,0x0000,0x0000,
	0x0000,0x0000,0x0000,0x0000,0x0000,0x003c,0x0000,0x0000,
	0x0000,0x0000,0x0000,0x0000,0x0000,0x0000,0x0000,0x0000
</mem_w>

#MOT17 "ID18"
<medit>	<motor name="ID18" data="17"/>
</medit>
<mem_w size="2" adr="0x1440">
	0x0da2,0x0c44,0x0c46,0x0d22,0x0100,0x01b3,0x8001,0x7fff,
	0x0000,0x0000,0x0000,0x0000,0x0000,0x0000,0x0000,0x0000,
	0x0000,0x0000,0x0000,0x0000,0x0000,0x003c,0x0000,0x0000,
	0x0000,0x0000,0x0000,0x0000,0x0000,0x0000,0x0000,0x0000
</mem_w>

#MOT18 "ID19"
<medit>	<motor name="ID19" data="18"/>
</medit>
<mem_w size="2" adr="0x1480">
	0x0da4,0x0c48,0x0c4a,0x0d24,0x0100,0x0032,0x8001,0x7fff,
	0x0000,0x0000,0x0000,0x0000,0x0000,0x0000,0x0000,0x0000,
	0x0000,0x0000,0x0000,0x0000,0x0000,0x003c,0x0000,0x0000,
	0x0000,0x0000,0x0000,0x0000,0x0000,0x0000,0x0000,0x0000
</mem_w>

#MOT19 "ID20"
<medit>	<motor name="ID20" data="19"/>
</medit>
<mem_w size="2" adr="0x14c0">
	0x0da6,0x0c4c,0x0c4e,0x0d26,0x0100,0xfdb2,0x8001,0x7fff,
	0x0000,0x0000,0x0000,0x0000,0x0000,0x0000,0x0000,0x0000,
	0x0000,0x0000,0x0000,0x0000,0x0000,0x003c,0x0000,0x0000,
	0x0000,0x0000,0x0000,0x0000,0x0000,0x0000,0x0000,0x0000
</mem_w>

#MOT20 "ID21"
<medit>	<motor name="ID21" data="20"/>
</medit>
<mem_w size="2" adr="0x1500">
	0x0da8,0x0c50,0x0c52,0x0d28,0x0100,0xfe61,0x8001,0x7fff,
	0x0000,0x0000,0x0000,0x0000,0x0000,0x0000,0x0000,0x0000,
	0x0000,0x0000,0x0000,0x0000,0x0000,0x003c,0x0000,0x0000,
	0x0000,0x0000,0x0000,0x0000,0x0000,0x0000,0x0000,0x0000
</mem_w>

#MOT21 "ID22"
<medit>	<motor name="ID22" data="21"/>
</medit>
<mem_w size="2" adr="0x1540">
	0x0daa,0x0c54,0x0c56,0x0d2a,0x0100,0x0000,0x8001,0x7fff,
	0x0000,0x0000,0x0000,0x0000,0x0000,0x0000,0x0000,0x0000,
	0x0000,0x0000,0x0000,0x0000,0x0000,0x0000,0x0000,0x0000,
	0x0000,0x0000,0x0000,0x0000,0x0000,0x0000,0x0000,0x0000
</mem_w>

#MOT22 "ID23"
<medit>	<motor name="ID23" data="22"/>
</medit>
<mem_w size="2" adr="0x1580">
	0x0dac,0x0c58,0x0c5a,0x0d2c,0x0100,0x0000,0x8001,0x7fff,
	0x0000,0x0000,0x0000,0x0000,0x0000,0x0000,0x0000,0x0000,
	0x0000,0x0000,0x0000,0x0000,0x0000,0x0000,0x0000,0x0000,
	0x0000,0x0000,0x0000,0x0000,0x0000,0x0000,0x0000,0x0000
</mem_w>

#MOT23 "ID24"
<medit>	<motor name="ID24" data="23"/>
</medit>
<mem_w size="2" adr="0x15c0">
	0x0dae,0x0c5c,0x0c5e,0x0d2e,0x0100,0x0000,0x8001,0x7fff,
	0x0000,0x0000,0x0000,0x0000,0x0000,0x0000,0x0000,0x0000,
	0x0000,0x0000,0x0000,0x0000,0x0000,0x0000,0x0000,0x0000,
	0x0000,0x0000,0x0000,0x0000,0x0000,0x0000,0x0000,0x0000
</mem_w>

#MOT24 ""
<medit>	<motor name="" data="24"/>
</medit>
<mem_w size="2" adr="0x1600">
	0x0db0,0x0000,0x0000,0x0d30,0x0100,0x0000,0x8001,0x7fff,
	0x0000,0x0000,0x0000,0x0000,0x0000,0x0000,0x0000,0x0000,
	0x0000,0x0000,0x0000,0x0000,0x0000,0x0000,0x0000,0x0000,
	0x0000,0x0000,0x0000,0x0000,0x0000,0x0000,0x0000,0x0000
</mem_w>

#MOT25 ""
<medit>	<motor name="" data="25"/>
</medit>
<mem_w size="2" adr="0x1640">
	0x0db2,0x0000,0x0000,0x0d32,0x0100,0x0000,0x8001,0x7fff,
	0x0000,0x0000,0x0000,0x0000,0x0000,0x0000,0x0000,0x0000,
	0x0000,0x0000,0x0000,0x0000,0x0000,0x0000,0x0000,0x0000,
	0x0000,0x0000,0x0000,0x0000,0x0000,0x0000,0x0000,0x0000
</mem_w>

#MOT26 ""
<medit>	<motor name="" data="26"/>
</medit>
<mem_w size="2" adr="0x1680">
	0x0db4,0x0000,0x0000,0x0d34,0x0100,0x0000,0x8001,0x7fff,
	0x0000,0x0000,0x0000,0x0000,0x0000,0x0000,0x0000,0x0000,
	0x0000,0x0000,0x0000,0x0000,0x0000,0x0000,0x0000,0x0000,
	0x0000,0x0000,0x0000,0x0000,0x0000,0x0000,0x0000,0x0000
</mem_w>

#MOT27 ""
<medit>	<motor name="" data="27"/>
</medit>
<mem_w size="2" adr="0x16c0">
	0x0db6,0x0000,0x0000,0x0d36,0x0100,0x0000,0x8001,0x7fff,
	0x0000,0x0000,0x0000,0x0000,0x0000,0x0000,0x0000,0x0000,
	0x0000,0x0000,0x0000,0x0000,0x0000,0x0000,0x0000,0x0000,
	0x0000,0x0000,0x0000,0x0000,0x0000,0x0000,0x0000,0x0000
</mem_w>

#MOT28 ""
<medit>	<motor name="" data="28"/>
</medit>
<mem_w size="2" adr="0x1700">
	0x0db8,0x0000,0x0000,0x0d38,0x0100,0x0000,0x8001,0x7fff,
	0x0000,0x0000,0x0000,0x0000,0x0000,0x0000,0x0000,0x0000,
	0x0000,0x0000,0x0000,0x0000,0x0000,0x0000,0x0000,0x0000,
	0x0000,0x0000,0x0000,0x0000,0x0000,0x0000,0x0000,0x0000
</mem_w>

#MOT29 ""
<medit>	<motor name="" data="29"/>
</medit>
<mem_w size="2" adr="0x1740">
	0x0dba,0x0000,0x0000,0x0d3a,0x0100,0x0000,0x8001,0x7fff,
	0x0000,0x0000,0x0000,0x0000,0x0000,0x0000,0x0000,0x0000,
	0x0000,0x0000,0x0000,0x0000,0x0000,0x0000,0x0000,0x0000,
	0x0000,0x0000,0x0000,0x0000,0x0000,0x0000,0x0000,0x0000
</mem_w>

#MOT30 ""
<medit>	<motor name="" data="30"/>
</medit>
<mem_w size="2" adr="0x1780">
	0x0dbc,0x0000,0x0000,0x0d3c,0x0100,0x0000,0x8001,0x7fff,
	0x0000,0x0000,0x0000,0x0000,0x0000,0x0000,0x0000,0x0000,
	0x0000,0x0000,0x0000,0x0000,0x0000,0x0000,0x0000,0x0000,
	0x0000,0x0000,0x0000,0x0000,0x0000,0x0000,0x0000,0x0000
</mem_w>

#MOT31 ""
<medit>	<motor name="" data="31"/>
</medit>
<mem_w size="2" adr="0x17c0">
	0x0dbe,0x0000,0x0000,0x0d3e,0x0100,0x0000,0x8001,0x7fff,
	0x0000,0x0000,0x0000,0x0000,0x0000,0x0000,0x0000,0x0000,
	0x0000,0x0000,0x0000,0x0000,0x0000,0x0000,0x0000,0x0000,
	0x0000,0x0000,0x0000,0x0000,0x0000,0x0000,0x0000,0x0000
</mem_w>

#MOT32 ""
<medit>	<motor name="" data="32"/>
</medit>
<mem_w size="2" adr="0x1800">
	0x0dc0,0x0000,0x0000,0x0d40,0x0100,0x0000,0x8001,0x7fff,
	0x0000,0x0000,0x0000,0x0000,0x0000,0x0000,0x0000,0x0000,
	0x0000,0x0000,0x0000,0x0000,0x0000,0x0000,0x0000,0x0000,
	0x0000,0x0000,0x0000,0x0000,0x0000,0x0000,0x0000,0x0000
</mem_w>

#MOT33 ""
<medit>	<motor name="" data="33"/>
</medit>
<mem_w size="2" adr="0x1840">
	0x0dc2,0x0000,0x0000,0x0d42,0x0100,0x0000,0x8001,0x7fff,
	0x0000,0x0000,0x0000,0x0000,0x0000,0x0000,0x0000,0x0000,
	0x0000,0x0000,0x0000,0x0000,0x0000,0x0000,0x0000,0x0000,
	0x0000,0x0000,0x0000,0x0000,0x0000,0x0000,0x0000,0x0000
</mem_w>

#MOT34 ""
<medit>	<motor name="" data="34"/>
</medit>
<mem_w size="2" adr="0x1880">
	0x0dc4,0x0000,0x0000,0x0d44,0x0100,0x0000,0x8001,0x7fff,
	0x0000,0x0000,0x0000,0x0000,0x0000,0x0000,0x0000,0x0000,
	0x0000,0x0000,0x0000,0x0000,0x0000,0x0000,0x0000,0x0000,
	0x0000,0x0000,0x0000,0x0000,0x0000,0x0000,0x0000,0x0000
</mem_w>

#MOT35 ""
<medit>	<motor name="" data="35"/>
</medit>
<mem_w size="2" adr="0x18c0">
	0x0dc6,0x0000,0x0000,0x0d46,0x0100,0x0000,0x8001,0x7fff,
	0x0000,0x0000,0x0000,0x0000,0x0000,0x0000,0x0000,0x0000,
	0x0000,0x0000,0x0000,0x0000,0x0000,0x0000,0x0000,0x0000,
	0x0000,0x0000,0x0000,0x0000,0x0000,0x0000,0x0000,0x0000
</mem_w>

#MOT36 ""
<medit>	<motor name="" data="36"/>
</medit>
<mem_w size="2" adr="0x1900">
	0x0dc8,0x0000,0x0000,0x0d48,0x0100,0x0000,0x8001,0x7fff,
	0x0000,0x0000,0x0000,0x0000,0x0000,0x0000,0x0000,0x0000,
	0x0000,0x0000,0x0000,0x0000,0x0000,0x0000,0x0000,0x0000,
	0x0000,0x0000,0x0000,0x0000,0x0000,0x0000,0x0000,0x0000
</mem_w>

#MOT37 ""
<medit>	<motor name="" data="37"/>
</medit>
<mem_w size="2" adr="0x1940">
	0x0dca,0x0000,0x0000,0x0d4a,0x0100,0x0000,0x8001,0x7fff,
	0x0000,0x0000,0x0000,0x0000,0x0000,0x0000,0x0000,0x0000,
	0x0000,0x0000,0x0000,0x0000,0x0000,0x0000,0x0000,0x0000,
	0x0000,0x0000,0x0000,0x0000,0x0000,0x0000,0x0000,0x0000
</mem_w>

#MOT38 ""
<medit>	<motor name="" data="38"/>
</medit>
<mem_w size="2" adr="0x1980">
	0x0dcc,0x0000,0x0000,0x0d4c,0x0100,0x0000,0x8001,0x7fff,
	0x0000,0x0000,0x0000,0x0000,0x0000,0x0000,0x0000,0x0000,
	0x0000,0x0000,0x0000,0x0000,0x0000,0x0000,0x0000,0x0000,
	0x0000,0x0000,0x0000,0x0000,0x0000,0x0000,0x0000,0x0000
</mem_w>

#MOT39 ""
<medit>	<motor name="" data="39"/>
</medit>
<mem_w size="2" adr="0x19c0">
	0x0dce,0x0000,0x0000,0x0d4e,0x0100,0x0000,0x8001,0x7fff,
	0x0000,0x0000,0x0000,0x0000,0x0000,0x0000,0x0000,0x0000,
	0x0000,0x0000,0x0000,0x0000,0x0000,0x0000,0x0000,0x0000,
	0x0000,0x0000,0x0000,0x0000,0x0000,0x0000,0x0000,0x0000
</mem_w>

#MOT40 ""
<medit>	<motor name="" data="40"/>
</medit>
<mem_w size="2" adr="0x1a00">
	0x0dd0,0x0000,0x0000,0x0d50,0x0100,0x0000,0x8001,0x7fff,
	0x0000,0x0000,0x0000,0x0000,0x0000,0x0000,0x0000,0x0000,
	0x0000,0x0000,0x0000,0x0000,0x0000,0x0000,0x0000,0x0000,
	0x0000,0x0000,0x0000,0x0000,0x0000,0x0000,0x0000,0x0000
</mem_w>

#MOT41 ""
<medit>	<motor name="" data="41"/>
</medit>
<mem_w size="2" adr="0x1a40">
	0x0dd2,0x0000,0x0000,0x0d52,0x0100,0x0000,0x8001,0x7fff,
	0x0000,0x0000,0x0000,0x0000,0x0000,0x0000,0x0000,0x0000,
	0x0000,0x0000,0x0000,0x0000,0x0000,0x0000,0x0000,0x0000,
	0x0000,0x0000,0x0000,0x0000,0x0000,0x0000,0x0000,0x0000
</mem_w>

#MOT42 ""
<medit>	<motor name="" data="42"/>
</medit>
<mem_w size="2" adr="0x1a80">
	0x0dd4,0x0000,0x0000,0x0d54,0x0100,0x0000,0x8001,0x7fff,
	0x0000,0x0000,0x0000,0x0000,0x0000,0x0000,0x0000,0x0000,
	0x0000,0x0000,0x0000,0x0000,0x0000,0x0000,0x0000,0x0000,
	0x0000,0x0000,0x0000,0x0000,0x0000,0x0000,0x0000,0x0000
</mem_w>

#MOT43 ""
<medit>	<motor name="" data="43"/>
</medit>
<mem_w size="2" adr="0x1ac0">
	0x0dd6,0x0000,0x0000,0x0d56,0x0100,0x0000,0x8001,0x7fff,
	0x0000,0x0000,0x0000,0x0000,0x0000,0x0000,0x0000,0x0000,
	0x0000,0x0000,0x0000,0x0000,0x0000,0x0000,0x0000,0x0000,
	0x0000,0x0000,0x0000,0x0000,0x0000,0x0000,0x0000,0x0000
</mem_w>

#MOT44 ""
<medit>	<motor name="" data="44"/>
</medit>
<mem_w size="2" adr="0x1b00">
	0x0dd8,0x0000,0x0000,0x0d58,0x0100,0x0000,0x8001,0x7fff,
	0x0000,0x0000,0x0000,0x0000,0x0000,0x0000,0x0000,0x0000,
	0x0000,0x0000,0x0000,0x0000,0x0000,0x0000,0x0000,0x0000,
	0x0000,0x0000,0x0000,0x0000,0x0000,0x0000,0x0000,0x0000
</mem_w>

#MOT45 ""
<medit>	<motor name="" data="45"/>
</medit>
<mem_w size="2" adr="0x1b40">
	0x0dda,0x0000,0x0000,0x0d5a,0x0100,0x0000,0x8001,0x7fff,
	0x0000,0x0000,0x0000,0x0000,0x0000,0x0000,0x0000,0x0000,
	0x0000,0x0000,0x0000,0x0000,0x0000,0x0000,0x0000,0x0000,
	0x0000,0x0000,0x0000,0x0000,0x0000,0x0000,0x0000,0x0000
</mem_w>

#MOT46 ""
<medit>	<motor name="" data="46"/>
</medit>
<mem_w size="2" adr="0x1b80">
	0x0ddc,0x0000,0x0000,0x0d5c,0x0100,0x0000,0x8001,0x7fff,
	0x0000,0x0000,0x0000,0x0000,0x0000,0x0000,0x0000,0x0000,
	0x0000,0x0000,0x0000,0x0000,0x0000,0x0000,0x0000,0x0000,
	0x0000,0x0000,0x0000,0x0000,0x0000,0x0000,0x0000,0x0000
</mem_w>

#MOT47 ""
<medit>	<motor name="" data="47"/>
</medit>
<mem_w size="2" adr="0x1bc0">
	0x0dde,0x0000,0x0000,0x0d5e,0x0100,0x0000,0x8001,0x7fff,
	0x0000,0x0000,0x0000,0x0000,0x0000,0x0000,0x0000,0x0000,
	0x0000,0x0000,0x0000,0x0000,0x0000,0x0000,0x0000,0x0000,
	0x0000,0x0000,0x0000,0x0000,0x0000,0x0000,0x0000,0x0000
</mem_w>

#MOT48 ""
<medit>	<motor name="" data="48"/>
</medit>
<mem_w size="2" adr="0x1c00">
	0x0de0,0x0000,0x0000,0x0d60,0x0100,0x0000,0x8001,0x7fff,
	0x0000,0x0000,0x0000,0x0000,0x0000,0x0000,0x0000,0x0000,
	0x0000,0x0000,0x0000,0x0000,0x0000,0x0000,0x0000,0x0000,
	0x0000,0x0000,0x0000,0x0000,0x0000,0x0000,0x0000,0x0000
</mem_w>

#MOT49 ""
<medit>	<motor name="" data="49"/>
</medit>
<mem_w size="2" adr="0x1c40">
	0x0de2,0x0000,0x0000,0x0d62,0x0100,0x0000,0x8001,0x7fff,
	0x0000,0x0000,0x0000,0x0000,0x0000,0x0000,0x0000,0x0000,
	0x0000,0x0000,0x0000,0x0000,0x0000,0x0000,0x0000,0x0000,
	0x0000,0x0000,0x0000,0x0000,0x0000,0x0000,0x0000,0x0000
</mem_w>

#MOT50 ""
<medit>	<motor name="" data="50"/>
</medit>
<mem_w size="2" adr="0x1c80">
	0x0de4,0x0000,0x0000,0x0d64,0x0100,0x0000,0x8001,0x7fff,
	0x0000,0x0000,0x0000,0x0000,0x0000,0x0000,0x0000,0x0000,
	0x0000,0x0000,0x0000,0x0000,0x0000,0x0000,0x0000,0x0000,
	0x0000,0x0000,0x0000,0x0000,0x0000,0x0000,0x0000,0x0000
</mem_w>

#MOT51 ""
<medit>	<motor name="" data="51"/>
</medit>
<mem_w size="2" adr="0x1cc0">
	0x0de6,0x0000,0x0000,0x0d66,0x0100,0x0000,0x8001,0x7fff,
	0x0000,0x0000,0x0000,0x0000,0x0000,0x0000,0x0000,0x0000,
	0x0000,0x0000,0x0000,0x0000,0x0000,0x0000,0x0000,0x0000,
	0x0000,0x0000,0x0000,0x0000,0x0000,0x0000,0x0000,0x0000
</mem_w>

#MOT52 ""
<medit>	<motor name="" data="52"/>
</medit>
<mem_w size="2" adr="0x1d00">
	0x0de8,0x0000,0x0000,0x0d68,0x0100,0x0000,0x8001,0x7fff,
	0x0000,0x0000,0x0000,0x0000,0x0000,0x0000,0x0000,0x0000,
	0x0000,0x0000,0x0000,0x0000,0x0000,0x0000,0x0000,0x0000,
	0x0000,0x0000,0x0000,0x0000,0x0000,0x0000,0x0000,0x0000
</mem_w>

#MOT53 ""
<medit>	<motor name="" data="53"/>
</medit>
<mem_w size="2" adr="0x1d40">
	0x0dea,0x0000,0x0000,0x0d6a,0x0100,0x0000,0x8001,0x7fff,
	0x0000,0x0000,0x0000,0x0000,0x0000,0x0000,0x0000,0x0000,
	0x0000,0x0000,0x0000,0x0000,0x0000,0x0000,0x0000,0x0000,
	0x0000,0x0000,0x0000,0x0000,0x0000,0x0000,0x0000,0x0000
</mem_w>

#MOT54 ""
<medit>	<motor name="" data="54"/>
</medit>
<mem_w size="2" adr="0x1d80">
	0x0dec,0x0000,0x0000,0x0d6c,0x0100,0x0000,0x8001,0x7fff,
	0x0000,0x0000,0x0000,0x0000,0x0000,0x0000,0x0000,0x0000,
	0x0000,0x0000,0x0000,0x0000,0x0000,0x0000,0x0000,0x0000,
	0x0000,0x0000,0x0000,0x0000,0x0000,0x0000,0x0000,0x0000
</mem_w>

#MOT55 ""
<medit>	<motor name="" data="55"/>
</medit>
<mem_w size="2" adr="0x1dc0">
	0x0dee,0x0000,0x0000,0x0d6e,0x0100,0x0000,0x8001,0x7fff,
	0x0000,0x0000,0x0000,0x0000,0x0000,0x0000,0x0000,0x0000,
	0x0000,0x0000,0x0000,0x0000,0x0000,0x0000,0x0000,0x0000,
	0x0000,0x0000,0x0000,0x0000,0x0000,0x0000,0x0000,0x0000
</mem_w>

#MOT56 ""
<medit>	<motor name="" data="56"/>
</medit>
<mem_w size="2" adr="0x1e00">
	0x0df0,0x0000,0x0000,0x0d70,0x0100,0x0000,0x8001,0x7fff,
	0x0000,0x0000,0x0000,0x0000,0x0000,0x0000,0x0000,0x0000,
	0x0000,0x0000,0x0000,0x0000,0x0000,0x0000,0x0000,0x0000,
	0x0000,0x0000,0x0000,0x0000,0x0000,0x0000,0x0000,0x0000
</mem_w>

#MOT57 ""
<medit>	<motor name="" data="57"/>
</medit>
<mem_w size="2" adr="0x1e40">
	0x0df2,0x0000,0x0000,0x0d72,0x0100,0x0000,0x8001,0x7fff,
	0x0000,0x0000,0x0000,0x0000,0x0000,0x0000,0x0000,0x0000,
	0x0000,0x0000,0x0000,0x0000,0x0000,0x0000,0x0000,0x0000,
	0x0000,0x0000,0x0000,0x0000,0x0000,0x0000,0x0000,0x0000
</mem_w>

#MOT58 ""
<medit>	<motor name="" data="58"/>
</medit>
<mem_w size="2" adr="0x1e80">
	0x0df4,0x0000,0x0000,0x0d74,0x0100,0x0000,0x8001,0x7fff,
	0x0000,0x0000,0x0000,0x0000,0x0000,0x0000,0x0000,0x0000,
	0x0000,0x0000,0x0000,0x0000,0x0000,0x0000,0x0000,0x0000,
	0x0000,0x0000,0x0000,0x0000,0x0000,0x0000,0x0000,0x0000
</mem_w>

#MOT59 ""
<medit>	<motor name="" data="59"/>
</medit>
<mem_w size="2" adr="0x1ec0">
	0x0df6,0x0000,0x0000,0x0d76,0x0100,0x0000,0x8001,0x7fff,
	0x0000,0x0000,0x0000,0x0000,0x0000,0x0000,0x0000,0x0000,
	0x0000,0x0000,0x0000,0x0000,0x0000,0x0000,0x0000,0x0000,
	0x0000,0x0000,0x0000,0x0000,0x0000,0x0000,0x0000,0x0000
</mem_w>

#MOT60 ""
<medit>	<motor name="" data="60"/>
</medit>
<mem_w size="2" adr="0x1f00">
	0x0df8,0x0000,0x0000,0x0d78,0x0100,0x0000,0x8001,0x7fff,
	0x0000,0x0000,0x0000,0x0000,0x0000,0x0000,0x0000,0x0000,
	0x0000,0x0000,0x0000,0x0000,0x0000,0x0000,0x0000,0x0000,
	0x0000,0x0000,0x0000,0x0000,0x0000,0x0000,0x0000,0x0000
</mem_w>

#MOT61 ""
<medit>	<motor name="" data="61"/>
</medit>
<mem_w size="2" adr="0x1f40">
	0x0dfa,0x0000,0x0000,0x0d7a,0x0100,0x0000,0x8001,0x7fff,
	0x0000,0x0000,0x0000,0x0000,0x0000,0x0000,0x0000,0x0000,
	0x0000,0x0000,0x0000,0x0000,0x0000,0x0000,0x0000,0x0000,
	0x0000,0x0000,0x0000,0x0000,0x0000,0x0000,0x0000,0x0000
</mem_w>

#MOT62 ""
<medit>	<motor name="" data="62"/>
</medit>
<mem_w size="2" adr="0x1f80">
	0x0dfc,0x0000,0x0000,0x0d7c,0x0100,0x0000,0x8001,0x7fff,
	0x0000,0x0000,0x0000,0x0000,0x0000,0x0000,0x0000,0x0000,
	0x0000,0x0000,0x0000,0x0000,0x0000,0x0000,0x0000,0x0000,
	0x0000,0x0000,0x0000,0x0000,0x0000,0x0000,0x0000,0x0000
</mem_w>

#MOT63 ""
<medit>	<motor name="" data="63"/>
</medit>
<mem_w size="2" adr="0x1fc0">
	0x0dfe,0x0000,0x0000,0x0d7e,0x0100,0x0000,0x8001,0x7fff,
	0x0000,0x0000,0x0000,0x0000,0x0000,0x0000,0x0000,0x0000,
	0x0000,0x0000,0x0000,0x0000,0x0000,0x0000,0x0000,0x0000,
	0x0000,0x0000,0x0000,0x0000,0x0000,0x0000,0x0000,0x0000
</mem_w>


#補間バッファのリセット
<mem_w size="1" adr="0x0b44">1</mem_w>

#サーボのオーバーライド値（0x8000で初期化）
<mem_w size="2" adr="0x0d00">
	0x8000,0x8000,0x8000,0x8000,0x8000,0x8000,
	0x8000,0x8000,0x8000,0x8000,0x8000,0x8000,
	0x8000,0x8000,0x8000,0x8000,0x8000,0x8000,
	0x8000,0x8000,0x8000,0x8000,0x8000,0x8000,
	0x8000,0x8000,0x8000,0x8000,0x8000,0x8000,
	0x8000,0x8000,0x8000,0x8000,0x8000,0x8000,
	0x8000,0x8000,0x8000,0x8000,0x8000,0x8000,
	0x8000,0x8000,0x8000,0x8000,0x8000,0x8000,
	0x8000,0x8000,0x8000,0x8000,0x8000,0x8000,
	0x8000,0x8000,0x8000,0x8000,0x8000,0x8000,
	0x8000,0x8000,0x8000,0x8000
</mem_w>

#LEDのポーズスライダ設定
<mem_w size="2" adr="0x0e20">
	0x0c80,0x0c82,0x0c84,0x0c86,0x0c88,0x0c8a,0x0c8c,0x0c8c,
	0x008a,0x008a,0x008a,0x008a,0x008a,0x008a,0x008a,0x008a,
	0x0000,0x0000,0x0000,0x0000,0x0000,0x0000,0x0c8e,0x0c8e
</mem_w>

#サーボモータをONにする
<mem_w size="2" adr="0x0048">0x0001</mem_w>

#起動モーションの設定
<jump filename="main5_InitFlag確認補完無し_シーン1固定0415_test2.RM4"/>

